CHANGES.txt
COPYRIGHT.txt
LICENSE.txt
README.txt
bootstrap.py
buildout.cfg
setup.py
src/zc/__init__.py
src/zc.vault.egg-info/PKG-INFO
src/zc.vault.egg-info/SOURCES.txt
src/zc.vault.egg-info/dependency_links.txt
src/zc.vault.egg-info/namespace_packages.txt
src/zc.vault.egg-info/not-zip-safe
src/zc.vault.egg-info/requires.txt
src/zc.vault.egg-info/top_level.txt
src/zc/vault/README.txt
src/zc/vault/__init__.py
src/zc/vault/catalog.py
src/zc/vault/catalog.txt
src/zc/vault/catalog.zcml
src/zc/vault/configure.zcml
src/zc/vault/core.py
src/zc/vault/i18n.py
src/zc/vault/interfaces.py
src/zc/vault/keyref.py
src/zc/vault/objectlog.py
src/zc/vault/objectlog.txt
src/zc/vault/objectlog.zcml
src/zc/vault/tests.py
src/zc/vault/traversal.py
src/zc/vault/traversal.txt
src/zc/vault/traversal.zcml
src/zc/vault/vault.py
src/zc/vault/versions.py
src/zc/vault/versions.txt
src/zc/vault/versions.zcml