Metadata-Version: 1.0
Name: zc.vault
Version: 0.11
Summary: Low-level versioning support
Home-page: http://pypi.python.org/pypi/zc.vault
Author: Zope Project
Author-email: zope-dev@zope.org
License: ZPL 2.1
Keywords: Zope Zope3 version control vault
Platform: UNKNOWN
Classifier: Development Status :: 5 - Production/Stable
Classifier: Environment :: Web Environment
Classifier: Framework :: Zope3
Classifier: Intended Audience :: Developers
Classifier: License :: OSI Approved :: Zope Public License
Classifier: Natural Language :: English
Classifier: Operating System :: OS Independent
Classifier: Programming Language :: Python
Classifier: Topic :: Internet :: WWW/HTTP
Classifier: Topic :: Software Development :: Libraries :: Python Modules
